cal/__init__.py
cal/cal.py
tux_cal-0.1.4.dist-info/entry_points.txt
tux_cal-0.1.4.dist-info/METADATA
tux_cal-0.1.4.dist-info/WHEEL
tux_cal-0.1.4.dist-info/RECORD
