Metadata-Version: 2.1
Name: tux-cal
Version: 0.1.4
Summary: A simple calendar tool mimicking Unix 'cal' command.
License: MIT
Author: Estevao Fonseca
Author-email: estevaopfon@gmail.com
Requires-Python: >=3.8,<4.0
Classifier: License :: OSI Approved :: MIT License
Classifier: Programming Language :: Python :: 3
Classifier: Programming Language :: Python :: 3.8
Classifier: Programming Language :: Python :: 3.9
Classifier: Programming Language :: Python :: 3.10
Classifier: Programming Language :: Python :: 3.11
